CONVERTING_TO_5.0.0
Changelog
LICENSE
MANIFEST.in
README.md
README.rst
example.py
requirements.txt
setup.py
IndexedRedis/IRQueryableList.py
IndexedRedis/__init__.py
IndexedRedis/compat_convert.py
IndexedRedis/compat_str.py
IndexedRedis/deprecated.py
IndexedRedis/timed.py
IndexedRedis/utils.py
IndexedRedis/fields/FieldValueTypes.py
IndexedRedis/fields/__init__.py
IndexedRedis/fields/b64.py
IndexedRedis/fields/bytes_field.py
IndexedRedis/fields/chain.py
IndexedRedis/fields/classic.py
IndexedRedis/fields/compressed.py
IndexedRedis/fields/fixedpoint.py
IndexedRedis/fields/foreign.py
IndexedRedis/fields/null.py
IndexedRedis/fields/pickle_field.py
IndexedRedis/fields/raw.py
IndexedRedis/fields/unicode_field.py
indexedredis.egg-info/PKG-INFO
indexedredis.egg-info/SOURCES.txt
indexedredis.egg-info/dependency_links.txt
indexedredis.egg-info/requires.txt
indexedredis.egg-info/top_level.txt
patches/README
patches/apply_patch.sh
patches/extra_lua_filters.patch
patches/factory.patch
patches/single_pipeline_foreign.patch
tests/README
tests/runTests.py
tests/x.py
tests/UnitTests/TestProperties.py
tests/UnitTests/test_CopyModel.py
tests/UnitTests/test_HashedIndexes.py
tests/UnitTests/test_IRBase64Field.py
tests/UnitTests/test_IRBytesField.py
tests/UnitTests/test_IRCompressedField.py
tests/UnitTests/test_IRDefaultValues.py
tests/UnitTests/test_IRField.py
tests/UnitTests/test_IRFieldChain.py
tests/UnitTests/test_IRFixedPointField.py
tests/UnitTests/test_IRForeignLinkField.py
tests/UnitTests/test_IRForeignMultiLinkField.py
tests/UnitTests/test_IRPickleField.py
tests/UnitTests/test_IRRawField.py
tests/UnitTests/test_IRUnicodeField.py
tests/UnitTests/test_ModelDiff.py
tests/UnitTests/test_ModelValidation.py
tests/UnitTests/test_SimpleSetAndGet.py
tests/simple/README
tests/simple/RUN_ME.py
tests/simple/example.py
tests/simple/testChain.py
tests/simple/testCompress.py
tests/simple/testDatetime.py
tests/simple/testFixedPoint.py
tests/simple/testJson.py
tests/simple/testPickle.py
tests/simple/testRaw.py
tests/simple/testUnicode.py
tests/simple/testUnicode64.py
tests/simple/IndexedRedis/IRQueryableList.py
tests/simple/IndexedRedis/__init__.py
