Metadata-Version: 1.1
Name: indexedredis
Version: 6.0.3
Summary: A super-fast ORM backed by Redis, supporting models and indexes with O(1) searches, and support for storing native/complex types and objects
Home-page: https://github.com/kata198/indexedredis
Author: Tim Savannah
Author-email: kata198@gmail.com
License: LGPLv2
Keywords: redis,IndexedRedis,SQL,nosql,orm,fast,python,filter,index,model
Platform: UNKNOWN
Classifier: Development Status :: 5 - Production/Stable
Classifier: Programming Language :: Python
Classifier: License :: OSI Approved :: GNU Lesser General Public License v2 (LGPLv2)
Classifier: Programming Language :: Python :: 2
Classifier: Programming Language :: Python :: 2.7
Classifier: Programming Language :: Python :: 3
Classifier: Programming Language :: Python :: 3.4
Classifier: Programming Language :: Python :: 3.5
Classifier: Programming Language :: Python :: 3.6
Classifier: Topic :: Database :: Front-Ends
Classifier: Topic :: Software Development :: Libraries :: Python Modules
Requires: redis
Requires: QueryableList
Provides: indexedredis
